drb/drivers/era5/__init__.py
drb/drivers/era5/_version.py
drb/drivers/era5/era5.py
drb/exceptions/era5.py
drb/topics/era5/__init__.py
drb/topics/era5/cortex.yml
drb_driver_era5-1.3.0.dist-info/LICENCE.txt
drb_driver_era5-1.3.0.dist-info/METADATA
drb_driver_era5-1.3.0.dist-info/WHEEL
drb_driver_era5-1.3.0.dist-info/entry_points.txt
drb_driver_era5-1.3.0.dist-info/top_level.txt
drb_driver_era5-1.3.0.dist-info/RECORD
