Metadata-Version: 2.1
Name: drb-driver-era5
Version: 1.3.0
Summary: DRB era5 OGC Service driver
Author: GAEL Systems
Author-email: drb-python@gael.fr
License: LGPLv3
Project-URL: Documentation, http://drb-python.gitlab.io/impl/era5
Project-URL: Source, https://gitlab.com/drb-python/impl/era5
Classifier: Programming Language :: Python :: 3.8
Classifier: Environment :: Plugins
Classifier: License :: OSI Approved :: GNU Lesser General Public License v3 (LGPLv3)
Requires-Python: >=3.8
License-File: LICENCE.txt
Requires-Dist: drb ~=2.2.0
Requires-Dist: drb-driver-http ~=1.3.1
Requires-Dist: drb-driver-netcdf ~=1.3.0
Requires-Dist: cdsapi ==0.5.1
